steamgameoptions/__init__.py
steamgameoptions/client.py
steamgameoptions-0.1.1.dist-info/METADATA
steamgameoptions-0.1.1.dist-info/WHEEL
steamgameoptions-0.1.1.dist-info/top_level.txt
steamgameoptions-0.1.1.dist-info/RECORD
