Metadata-Version: 2.4
Name: steamgameoptions
Version: 0.1.1
Summary: A simple package for interacting with Steam
Author-email: Crazy_Jarle <revwsbwwp@inbox.lv>
License: MIT
Requires-Python: >=3.7
Requires-Dist: requests
Requires-Dist: python-dotenv
